mpxpy/__init__.py
mpxpy/auth.py
mpxpy/conversion.py
mpxpy/errors.py
mpxpy/file_batch.py
mpxpy/image.py
mpxpy/logger.py
mpxpy/mathpix_client.py
mpxpy/pdf.py
mpxpy/request_handler.py
mpxpy-0.0.18.dist-info/LICENSE.txt
mpxpy-0.0.18.dist-info/METADATA
mpxpy-0.0.18.dist-info/WHEEL
mpxpy-0.0.18.dist-info/top_level.txt
mpxpy-0.0.18.dist-info/RECORD
