Metadata-Version: 2.1
Name: mpxpy
Version: 0.0.18
Summary: Official Mathpix client for Python
Author-email: Nico Jimenez <nicodjimenez@mathpix.com>, Matt Chang <mattchang@mathpix.com>
License: MIT License
Project-URL: Homepage, https://github.com/Mathpix/mpxpy
Project-URL: Repository, https://github.com/Mathpix/mpxpy
Project-URL: Bug Tracker, https://github.com/Mathpix/mpxpy/issues
Keywords: mathpix,mpx,mpxpy,py,client,ocr,api,sdk,python,package,development
Classifier: Programming Language :: Python :: 3
Classifier: Programming Language :: Python :: 3.8
Classifier: Programming Language :: Python :: 3.9
Classifier: Programming Language :: Python :: 3.10
Classifier: Programming Language :: Python :: 3.11
Classifier: License :: OSI Approved :: MIT License
Classifier: Operating System :: OS Independent
Classifier: Intended Audience :: Developers
Classifier: Topic :: Software Development :: Libraries :: Python Modules
Requires-Python: >=3.8
License-File: LICENSE.txt
Requires-Dist: requests>=2.20.0
Requires-Dist: python-dotenv>=0.15.0
Requires-Dist: pydantic>=2.10.6
Provides-Extra: dev
Requires-Dist: pytest>=7.0.0; extra == "dev"
